osu/__init__.py
osu/events.py
osu/game.py
osu/tasks.py
osu/utils.py
osu/api/__init__.py
osu/api/client.py
osu/api/constants.py
osu/bancho/__init__.py
osu/bancho/client.py
osu/bancho/constants.py
osu/bancho/packets.py
osu/bancho/streams.py
osu/objects/__init__.py
osu/objects/beatmap.py
osu/objects/channel.py
osu/objects/client.py
osu/objects/collections.py
osu/objects/comment.py
osu/objects/lists.py
osu/objects/player.py
osu/objects/replays.py
osu/objects/score.py
osu/objects/status.py
osu/tcp/__init__.py
osu/tcp/bancho.py
osu/tcp/game.py
osu-1.4.13.dist-info/licenses/LICENSE
osu-1.4.13.dist-info/METADATA
osu-1.4.13.dist-info/WHEEL
osu-1.4.13.dist-info/top_level.txt
osu-1.4.13.dist-info/RECORD
