Metadata-Version: 2.4
Name: osu
Version: 1.4.13
Summary: A python library that emulates the osu! stable client
Author: Lekuru
Author-email: contact@lekuru.xyz
Keywords: osu,osugame,python,bancho
License-File: LICENSE
Requires-Dist: python-dateutil==2.9.0.post0
Requires-Dist: requests==2.32.3
Requires-Dist: psutil==7.0.0
Requires-Dist: wmi; platform_system == "Windows"
Dynamic: author
Dynamic: author-email
Dynamic: description
Dynamic: description-content-type
Dynamic: keywords
Dynamic: license-file
Dynamic: requires-dist
Dynamic: summary
